german_phoneme_validator/__init__.py
german_phoneme_validator/example_usage.py
german_phoneme_validator/test_refactoring_static.py
german_phoneme_validator/core/__init__.py
german_phoneme_validator/core/downloader.py
german_phoneme_validator/core/feature_extraction.py
german_phoneme_validator/core/models.py
german_phoneme_validator/core/validator.py
german_phoneme_validator-1.1.0.dist-info/METADATA
german_phoneme_validator-1.1.0.dist-info/WHEEL
german_phoneme_validator-1.1.0.dist-info/top_level.txt
german_phoneme_validator-1.1.0.dist-info/RECORD
