Metadata-Version: 2.4
Name: german-phoneme-validator
Version: 1.1.0
Summary: A production-ready Python module for acoustic validation of German phoneme pronunciation
Home-page: https://github.com/SergejKurtasch/german-phoneme-validator
Author: Sergej Kurtasch
Author-email: sergej.kurtasch@gmail.com
License: MIT
Project-URL: Documentation, https://github.com/SergejKurtasch/german-phoneme-validator#readme
Project-URL: Source, https://github.com/SergejKurtasch/german-phoneme-validator
Project-URL: Tracker, https://github.com/SergejKurtasch/german-phoneme-validator/issues
Keywords: phoneme validation,speech recognition,german language,acoustic analysis,pronunciation assessment
Classifier: Development Status :: 4 - Beta
Classifier: Intended Audience :: Developers
Classifier: Intended Audience :: Education
Classifier: Intended Audience :: Science/Research
Classifier: Topic :: Scientific/Engineering :: Artificial Intelligence
Classifier: Topic :: Software Development :: Libraries :: Python Modules
Classifier: Programming Language :: Python :: 3
Classifier: Programming Language :: Python :: 3.8
Classifier: Programming Language :: Python :: 3.9
Classifier: Programming Language :: Python :: 3.10
Classifier: Programming Language :: Python :: 3.11
Classifier: License :: OSI Approved :: MIT License
Classifier: Operating System :: OS Independent
Requires-Python: >=3.8
Provides-Extra: optional
Requires-Dist: parselmouth>=0.4.0; extra == "optional"
Requires-Dist: webrtcvad>=2.0.10; extra == "optional"
Requires-Dist: pandas>=1.3.0; extra == "optional"
Requires-Dist: tqdm>=4.64.0; extra == "optional"
Requires-Dist: torchaudio>=2.0.0; extra == "optional"
Provides-Extra: all
Dynamic: author
Dynamic: author-email
Dynamic: classifier
Dynamic: description
Dynamic: description-content-type
Dynamic: home-page
Dynamic: keywords
Dynamic: license
Dynamic: project-url
Dynamic: provides-extra
Dynamic: requires-python
Dynamic: summary
